yt2doc/__init__.py
yt2doc/__main__.py
yt2doc/cli.py
yt2doc/factories.py
yt2doc/timer.py
yt2doc/writer.py
yt2doc/yt2doc.py
yt2doc/extraction/__init__.py
yt2doc/extraction/extractor.py
yt2doc/extraction/file_cache.py
yt2doc/extraction/interfaces.py
yt2doc/formatting/__init__.py
yt2doc/formatting/formatter.py
yt2doc/formatting/interfaces.py
yt2doc/formatting/llm_adapter.py
yt2doc/formatting/llm_topic_segmenter.py
yt2doc/formatting/paragraphs_segmenter.py
yt2doc/formatting/template.md
yt2doc/i18n/__init__.py
yt2doc/i18n/punctuations.py
yt2doc/media/__init__.py
yt2doc/media/interfaces.py
yt2doc/media/media_info_extractor.py
yt2doc/transcription/__init__.py
yt2doc/transcription/faster_whisper_adapter.py
yt2doc/transcription/interfaces.py
yt2doc/transcription/transcriber.py
yt2doc/transcription/whisper_cpp_adapter.py
yt2doc-0.3.3.dist-info/METADATA
yt2doc-0.3.3.dist-info/WHEEL
yt2doc-0.3.3.dist-info/entry_points.txt
yt2doc-0.3.3.dist-info/licenses/LICENSE
yt2doc-0.3.3.dist-info/RECORD
